bumo/__init__.py
bumo/builder.py
bumo/color_palettes.py
bumo/colors.py
bumo/config.py
bumo/mode.py
bumo/mutation.py
bumo/shapes.py
bumo-0.1.3.dist-info/LICENSE
bumo-0.1.3.dist-info/METADATA
bumo-0.1.3.dist-info/WHEEL
bumo-0.1.3.dist-info/RECORD
