Metadata-Version: 2.1
Name: bumo
Version: 0.1.3
Summary: BUild123d Mutables Objects
Home-page: https://codeberg.org/roipoussiere/bumo
License: MIT
Keywords: cad,build123d
Author: Nathanaël Jourdane
Author-email: njourdane@protonmail.com
Requires-Python: >=3.11,<3.13
Classifier: Intended Audience :: Manufacturing
Classifier: License :: OSI Approved :: MIT License
Classifier: Operating System :: OS Independent
Classifier: Programming Language :: Python :: 3
Classifier: Programming Language :: Python :: 3.11
Classifier: Programming Language :: Python :: 3.12
Classifier: Topic :: Multimedia :: Graphics :: 3D Modeling
Classifier: Topic :: Scientific/Engineering
Requires-Dist: build123d (>=0.8.0,<0.9.0)
Requires-Dist: tabulate (>=0.9.0,<0.10.0)
Project-URL: Repository, https://codeberg.org/roipoussiere/bumo
